{"metadata": {"dbt_schema_version": "https://schemas.getdbt.com/dbt/run-results/v4.json", "dbt_version": "1.0.1", "generated_at": "2022-02-02T19:21:50.734198Z", "invocation_id": "8a4839af-84af-4a75-a59b-09462c38ea74", "env": {}}, "results": [{"status": "success", "timing": [{"name": "compile", "started_at": "2022-02-02T19:21:47.725016Z", "completed_at": "2022-02-02T19:21:48.805644Z"}, {"name": "execute", "started_at": "2022-02-02T19:21:48.830731Z", "completed_at": "2022-02-02T19:21:49.369982Z"}], "thread_id": "Thread-2", "execution_time": 1.8800201416015625, "adapter_response": {"_message": "SUCCESS 1", "code": "SUCCESS", "rows_affected": 1}, "message": "SUCCESS 1", "failures": null, "unique_id": "model.dbt_hd.using_packaged_tests"}, {"status": "success", "timing": [{"name": "compile", "started_at": "2022-02-02T19:21:47.725016Z", "completed_at": "2022-02-02T19:21:48.805644Z"}, {"name": "execute", "started_at": "2022-02-02T19:21:48.807632Z", "completed_at": "2022-02-02T19:21:50.255055Z"}], "thread_id": "Thread-1", "execution_time": 2.7598230838775635, "adapter_response": {"_message": "SUCCESS 1", "code": "SUCCESS", "rows_affected": 1}, "message": "SUCCESS 1", "failures": null, "unique_id": "model.dbt_hd.table_creation"}, {"status": "success", "timing": [{"name": "compile", "started_at": "2022-02-02T19:21:49.611291Z", "completed_at": "2022-02-02T19:21:49.618295Z"}, {"name": "execute", "started_at": "2022-02-02T19:21:49.619294Z", "completed_at": "2022-02-02T19:21:50.492965Z"}], "thread_id": "Thread-2", "execution_time": 1.102318286895752, "adapter_response": {"_message": "SUCCESS 1", "code": "SUCCESS", "rows_affected": 1}, "message": "SUCCESS 1", "failures": null, "unique_id": "model.dbt_hd.test_macro_col_values"}], "elapsed_time": 9.281449317932129, "args": {"write_json": true, "use_colors": true, "printer_width": 80, "version_check": true, "partial_parse": true, "static_parser": true, "profiles_dir": "C:\\Users\\waseem.peer\\.dbt", "send_anonymous_usage_stats": true, "event_buffer_size": 100000, "which": "run", "rpc_method": "run", "indirect_selection": "eager"}}